pyhtzee/__init__.py
pyhtzee/classes.py
pyhtzee/maps.py
pyhtzee/scoring.py
pyhtzee/state.py
pyhtzee/utils.py
pyhtzee-1.2.7.dist-info/LICENSE
pyhtzee-1.2.7.dist-info/METADATA
pyhtzee-1.2.7.dist-info/WHEEL
pyhtzee-1.2.7.dist-info/top_level.txt
pyhtzee-1.2.7.dist-info/RECORD
