Metadata-Version: 2.1
Name: pyhtzee
Version: 1.2.7
Summary: Yahtzee game engine
Home-page: https://github.com/villebro/pyhtzee
Author: Ville Brofeldt
Author-email: ville.brofeldt@iki.fi
Maintainer: Ville Brofeldt
Maintainer-email: ville.brofeldt@iki.fi
License: MIT
Platform: UNKNOWN
Classifier: Programming Language :: Python :: 3.6
Classifier: Programming Language :: Python :: 3.7
Classifier: Programming Language :: Python :: 3.8
Classifier: Intended Audience :: Developers
Classifier: License :: OSI Approved :: MIT License
Classifier: Natural Language :: English
